setup.py
lamiview/__init__.py
lamiview/app.py
lamiview/dialog_about.py
lamiview/dialog_progress.py
lamiview/lami.py
lamiview/main_window.py
lamiview/utils.py
lamiview.egg-info/PKG-INFO
lamiview.egg-info/SOURCES.txt
lamiview.egg-info/dependency_links.txt
lamiview.egg-info/entry_points.txt
lamiview.egg-info/requires.txt
lamiview.egg-info/top_level.txt
lamiview/res/ui/dialog_about.ui
lamiview/res/ui/dialog_progress.ui
lamiview/res/ui/main_window.ui