Metadata-Version: 1.0
Name: lamiview
Version: 0.0.1
Summary: LAMI viewer
Home-page: https://github.com/eepp/lamiview
Author: Philippe Proulx
Author-email: eeppeliteloop@gmail.com
License: MIT
Keywords: lttng-analyses lami
Platform: UNKNOWN
